bodhi/__init__.py
bodhi/core.py
bodhi/prompts.py
bodhi/types.py
bodhi/providers/__init__.py
bodhi/providers/openai.py
bodhi_llm-0.1.4.dist-info/METADATA
bodhi_llm-0.1.4.dist-info/WHEEL
bodhi_llm-0.1.4.dist-info/licenses/LICENSE
bodhi_llm-0.1.4.dist-info/RECORD
