Metadata-Version: 2.4
Name: bodhi-llm
Version: 0.1.4
Summary: BODHI: Epistemic virtues (curiosity and humility) for LLM responses
Project-URL: Homepage, https://github.com/sebasmos/bodhi-llms
Project-URL: Documentation, https://github.com/sebasmos/bodhi-llms#readme
Project-URL: Repository, https://github.com/sebasmos/bodhi-llms
Project-URL: Issues, https://github.com/sebasmos/bodhi-llms/issues
Author: Felipe Ocampo Osorio, Maximin Lange, Leo Anthony Celi, Janan Arslan, Kurt Benke, Rowell Castro, Gustavo Adolfo Cruz-Suarez, Roben Delos Reyes, Justin Engelmann, Ari Ercole, Almog Hilel, Mahima Kalla, Leo Kinyera, Torleif Markussen Lunde, Mackenzie J Meni, Anna E Premo, Jana Sedlakova, Pritika Vig
Author-email: Sebastián Andrés Cajas Ordóñez <sebasmos@mit.edu>
Maintainer-email: Sebastián Andrés Cajas Ordóñez <sebasmos@mit.edu>
License-Expression: CC-BY-NC-SA-4.0
License-File: LICENSE
Keywords: ai,curiosity,epistemic,healthcare,humility,llm,medical-ai,uncertainty
Classifier: Development Status :: 4 - Beta
Classifier: Intended Audience :: Developers
Classifier: Intended Audience :: Healthcare Industry
Classifier: Intended Audience :: Science/Research
Classifier: License :: Other/Proprietary License
Classifier: Operating System :: OS Independent
Classifier: Programming Language :: Python :: 3
Classifier: Programming Language :: Python :: 3.10
Classifier: Programming Language :: Python :: 3.11
Classifier: Programming Language :: Python :: 3.12
Classifier: Topic :: Scientific/Engineering :: Artificial Intelligence
Classifier: Topic :: Scientific/Engineering :: Medical Science Apps.
Requires-Python: >=3.10
Requires-Dist: httpx>=0.24.0
Provides-Extra: all
Requires-Dist: openai>=1.0.0; extra == 'all'
Provides-Extra: dev
Requires-Dist: openai>=1.0.0; extra == 'dev'
Requires-Dist: pytest-asyncio>=0.21.0; extra == 'dev'
Requires-Dist: pytest>=7.0.0; extra == 'dev'
Provides-Extra: openai
Requires-Dist: openai>=1.0.0; extra == 'openai'
